OxySDK.py
_OxySDK.cp310-win_amd64.pyd
OxySDK-1.1.5.6.dist-info/METADATA
OxySDK-1.1.5.6.dist-info/WHEEL
OxySDK-1.1.5.6.dist-info/top_level.txt
OxySDK-1.1.5.6.dist-info/RECORD
