Metadata-Version: 2.1
Name: OxySDK
Version: 1.1.5.6
Summary: OxySDK Python SDK
Home-page: UNKNOWN
Author: OxySound
Author-email: support@oxycom.co.uk
License: License :: Other/Proprietary License
Platform: UNKNOWN
Requires-Dist: pyaudio
Requires-Dist: numpy
